magic_kind/__init__.py
magic_kind/magic_kind.py
magic_kind-0.2.2.dist-info/LICENSE
magic_kind-0.2.2.dist-info/WHEEL
magic_kind-0.2.2.dist-info/METADATA
magic_kind-0.2.2.dist-info/RECORD
