Metadata-Version: 2.1
Name: magic-kind
Version: 0.2.2
Summary: The MagicKind type is a simpler alternative to Enum types for groups of related magic values when order is not important.
Home-page: https://github.com/aallaire/magic-kind
License: Apache-2.0
Author: andr3738
Author-email: andr3738@rackspace.com
Requires-Python: >=3.5,<4.0
Classifier: License :: OSI Approved :: Apache Software License
Classifier: Programming Language :: Python :: 3
Classifier: Programming Language :: Python :: 3.5
Classifier: Programming Language :: Python :: 3.6
Classifier: Programming Language :: Python :: 3.7
Classifier: Programming Language :: Python :: 3.8
Project-URL: Repository, https://github.com/aallaire/magic-kind
